iqplot/.gitignore
iqplot/__init__.py
iqplot/cat.py
iqplot/dist.py
iqplot/utils.py
iqplot/.ipynb_checkpoints/Untitled-checkpoint.ipynb
iqplot-0.3.7.dist-info/LICENSE
iqplot-0.3.7.dist-info/METADATA
iqplot-0.3.7.dist-info/WHEEL
iqplot-0.3.7.dist-info/top_level.txt
iqplot-0.3.7.dist-info/RECORD
