Metadata-Version: 2.1
Name: iqplot
Version: 0.3.7
Summary: Generate Bokeh plots for data sets with one quantitative variable.
Home-page: https://github.com/justinbois/iqplot
Download-URL: https://github.com/justinbois/iqplot/tarball/0.3.7
Author: Justin Bois
Author-email: bois@caltech.edu
License: BSD
Classifier: Development Status :: 4 - Beta
Classifier: Intended Audience :: Developers
Classifier: Programming Language :: Python :: 3
License-File: LICENSE
Requires-Dist: numpy
Requires-Dist: xarray
Requires-Dist: pandas
Requires-Dist: bokeh
Requires-Dist: colorcet
